README.md
setup.py
cleverutils/__init__.py
cleverutils/clevergui.py
cleverutils/cleversession.py
cleverutils/cleverutils.py
cleverutils/cleverweb.py
cleverutils/test_cleverutils.py
cleverutils.egg-info/PKG-INFO
cleverutils.egg-info/SOURCES.txt
cleverutils.egg-info/dependency_links.txt
cleverutils.egg-info/requires.txt
cleverutils.egg-info/top_level.txt