Metadata-Version: 2.1
Name: cleverutils
Version: 0.22.3
Summary: Some handy Python utilities and code snippets used repeatedly by the author and considered beginner to intermediate level of difficulty.  Published just in case they're of use to other Pythonistas somehwere, some time.
Home-page: https://github.com/Pfython/cleverutils
Author: Peter Fison
Author-email: peter@awsom.solutions
License: MIT License
Download-URL: https://github.com/Pfython/cleverutils/archive/0.22.3.tar.gz
Keywords: cleverutils utils,cleverdict,cleversession,selenium,keyring,pysimplegui
Platform: UNKNOWN
Classifier: Development Status :: 2 - Pre-Alpha
Classifier: Intended Audience :: Developers
Classifier: Operating System :: OS Independent
Classifier: Programming Language :: Python :: 3.6
Classifier: Programming Language :: Python :: 3.7
Classifier: Programming Language :: Python :: 3.8
Classifier: Programming Language :: Python :: 3.9
Classifier: Topic :: Communications
Classifier: Topic :: Communications :: Email
Classifier: Topic :: Internet
Classifier: Topic :: Internet :: WWW/HTTP
Classifier: Topic :: Internet :: WWW/HTTP :: Browsers
Classifier: Topic :: Internet :: WWW/HTTP :: Indexing/Search
Classifier: Topic :: Internet :: WWW/HTTP :: Session
Classifier: Topic :: Software Development
Classifier: Topic :: Software Development :: Build Tools
Classifier: Topic :: Software Development :: Libraries :: Python Modules
Classifier: Topic :: Software Development :: Object Brokering
Classifier: Topic :: Software Development :: User Interfaces
Classifier: Topic :: Software Development :: Version Control
Classifier: Topic :: System :: Archiving :: Backup
Classifier: Topic :: System :: Archiving :: Packaging
Classifier: Topic :: System :: Installation/Setup
Classifier: Topic :: System :: Networking
Classifier: Topic :: System :: Software Distribution
Classifier: Topic :: Utilities
Classifier: License :: OSI Approved :: MIT License
